<?xml version="1.0" encoding="UTF-8"?>

<channel name="xfce4-panel" version="1.0">
	<property name="configver" type="int" value="2"/>
	<property name="panels" type="array">
		<value type="int" value="1"/>
		<value type="int" value="2"/>
		<property name="panel-1" type="empty">
			<property name="autohide-behavior" type="uint" value="0"/>
			<property name="background-alpha" type="uint" value="100"/>
			<property name="background-style" type="uint" value="0"/>
			<property name="disable-struts" type="bool" value="false"/>
			<property name="enter-opacity" type="uint" value="88"/>
			<property name="leave-opacity" type="uint" value="61"/>
			<property name="length" type="uint" value="100"/>
			<property name="mode" type="uint" value="0"/>
			<property name="nrows" type="uint" value="1"/>
			<property name="plugin-ids" type="array">
				<value type="int" value="7"/>
				<value type="int" value="1"/>
				<value type="int" value="2"/>
				<value type="int" value="3"/>
				<value type="int" value="24"/>
				<value type="int" value="4"/>
				<value type="int" value="5"/>
				<value type="int" value="6"/>
				<value type="int" value="8"/>
				<value type="int" value="10"/>
				<value type="int" value="9"/>
				<value type="int" value="11"/>
				<value type="int" value="12"/>
				<value type="int" value="13"/>
				<value type="int" value="14"/>
			</property>
			<property name="position" type="string" value="p=8;x=720;y=703"/>
			<property name="position-locked" type="bool" value="true"/>
			<property name="size" type="uint" value="26"/>
		</property>
		<property name="panel-2" type="empty">
			<property name="autohide-behavior" type="uint" value="1"/>
			<property name="background-alpha" type="uint" value="100"/>
			<property name="background-style" type="uint" value="0"/>
			<property name="disable-struts" type="bool" value="false"/>
			<property name="enter-opacity" type="uint" value="88"/>
			<property name="leave-opacity" type="uint" value="60"/>
			<property name="length" type="uint" value="10"/>
			<property name="length-adjust" type="bool" value="true"/>
			<property name="mode" type="uint" value="1"/>
			<property name="nrows" type="uint" value="1"/>
			<property name="plugin-ids" type="array">
				<value type="int" value="15"/>
				<value type="int" value="16"/>
				<value type="int" value="17"/>
				<value type="int" value="21"/>
				<value type="int" value="22"/>
			</property>
			<property name="position" type="string" value="p=1;x=1415;y=316"/>
			<property name="position-locked" type="bool" value="false"/>
			<property name="size" type="uint" value="48"/>
		</property>
		<property name="dark-mode" type="bool" value="false"/>
	</property>
	<property name="plugins" type="empty">
		<property name="plugin-10" type="string" value="notification-plugin"/>
		<property name="plugin-11" type="string" value="separator">
			<property name="expand" type="bool" value="false"/>
			<property name="style" type="uint" value="0"/>
		</property>
		<property name="plugin-12" type="string" value="clock">
			<property name="digital-format" type="string" value="%a,%b %d,%R:%S"/>
			<property name="mode" type="uint" value="2"/>
			<property name="show-frame" type="bool" value="true"/>
			<property name="tooltip-format" type="string" value="%A %d %B %Y"/>
		</property>
		<property name="plugin-13" type="string" value="separator">
			<property name="expand" type="bool" value="false"/>
			<property name="style" type="uint" value="0"/>
		</property>
		<property name="plugin-14" type="string" value="actions">
			<property name="appearance" type="uint" value="1"/>
			<property name="ask-confirmation" type="bool" value="true"/>
		</property>
		<property name="plugin-15" type="string" value="showdesktop"/>
		<property name="plugin-16" type="string" value="separator">
			<property name="expand" type="bool" value="false"/>
			<property name="style" type="uint" value="1"/>
		</property>
		<property name="plugin-2" type="string" value="tasklist">
			<property name="grouping" type="uint" value="1"/>
		</property>
		<property name="plugin-21" type="string" value="separator">
			<property name="expand" type="bool" value="false"/>
			<property name="style" type="uint" value="1"/>
		</property>
		<property name="plugin-22" type="string" value="directorymenu">
			<property name="expand" type="bool" value="true"/>
			<property name="style" type="uint" value="0"/>
			<property name="base-directory" type="string" value="/root"/>
		</property>
		<property name="plugin-3" type="string" value="separator">
			<property name="expand" type="bool" value="true"/>
			<property name="style" type="uint" value="0"/>
		</property>
		<property name="plugin-4" type="string" value="pager">
			<property name="miniature-view" type="bool" value="true"/>
			<property name="rows" type="uint" value="1"/>
			<property name="workspace-scrolling" type="bool" value="false"/>
		</property>
		<property name="plugin-5" type="string" value="separator">
			<property name="expand" type="bool" value="false"/>
			<property name="style" type="uint" value="0"/>
		</property>
		<property name="plugin-6" type="string" value="systray">
			<property name="show-frame" type="bool" value="false"/>
			<property name="size-max" type="uint" value="22"/>
			<property name="square-icons" type="bool" value="true"/>
			<property name="names-ordered" type="array">
			</property>
			<property name="known-items" type="array">
				<value type="string" value="Fcitx"/>
			</property>
		</property>
		<property name="plugin-8" type="string" value="pulseaudio">
			<property name="enable-keyboard-shortcuts" type="bool" value="true"/>
			<property name="show-notifications" type="bool" value="true"/>
		</property>
		<property name="plugin-7" type="string" value="whiskermenu"/>
		<property name="plugin-1" type="string" value="applicationsmenu">
			<property name="button-icon" type="string" value="org.xfce.settings.default-applications"/>
		</property>
		<property name="plugin-24" type="string" value="xfce4-clipman-plugin"/>
		<property name="plugin-17" type="string" value="screenshooter"/>
		<property name="plugin-9" type="string" value="power-manager-plugin"/>
	</property>
</channel>
